{
  "trinity_enhanced_architecture": {
    "version": "4.1",
    "description": "Enhanced Trinity with salvaged production infrastructure",
    "integration_date": "2025-07-27",
    "salvaged_components": {
      "production_infrastructure": "infrastructure/ -> trinity/infrastructure/",
      "gitops_deployment": "kubernetes/ -> trinity/kubernetes/",
      "web_interface": "FRONTEND/ui-solidjs/ -> trinity/web-ui/",
      "rust_foundation": "platform/rust_engine/ -> trinity/core/phase1/"
    },
    "trinity_phases": {
      "phase_1": "Foundation + Enhanced Rust engine",
      "phase_2": "Conversational AI",
      "phase_3": "Termux API Multi-Modal",
      "phase_4": "True Intent Resonance + DRAP Orchestration"
    },
    "production_ready": {
      "infrastructure": "Complete GCP/K8s Terraform",
      "deployment": "ArgoCD GitOps pipeline",
      "monitoring": "Trinity monitoring dashboard",
      "web_interface": "Modern SolidJS control panel"
    }
  }
}
